pipeline_func.py
pipeline_func-1.0.0.dist-info/WHEEL
pipeline_func-1.0.0.dist-info/METADATA
pipeline_func-1.0.0.dist-info/RECORD
