Metadata-Version: 2.1
Name: pipeline_func
Version: 1.0.0
Summary: A utility for calling functions in pipelines.
Author-email: Kale Kundert <kale@thekunderts.net>
Requires-Python: ~=3.0
Classifier: Programming Language :: Python :: 3
Requires-Dist: pytest ; extra == "test"
Requires-Dist: polars ; extra == "test"
Project-URL: Bug Tracker, https://github.com/kalekundert/pipeline_func/issues
Project-URL: Continuous Integration, https://github.com/kalekundert/pipeline_func/actions
Project-URL: Test Coverage, https://app.codecov.io/github/kalekundert/pipeline_func
Project-URL: Version Control, https://github.com/kalekundert/pipeline_func
Provides-Extra: test
